CHANGES.txt
MANIFEST.in
README.txt
setup.py
src/collective/__init__.py
src/collective.recipe.platform.egg-info/PKG-INFO
src/collective.recipe.platform.egg-info/SOURCES.txt
src/collective.recipe.platform.egg-info/dependency_links.txt
src/collective.recipe.platform.egg-info/entry_points.txt
src/collective.recipe.platform.egg-info/namespace_packages.txt
src/collective.recipe.platform.egg-info/requires.txt
src/collective.recipe.platform.egg-info/top_level.txt
src/collective/recipe/__init__.py
src/collective/recipe/platform/README.txt
src/collective/recipe/platform/__init__.py
src/collective/recipe/platform/tests/__init__.py
src/collective/recipe/platform/tests/test_docs.py