Metadata-Version: 1.0
Name: collective.recipe.platform
Version: 0.1
Summary: Provide buildout variables with platform specific values.
Home-page: http://pypi.python.org/pypi/collective.recipe.platform
Author: Gerhard Weis
Author-email: gerhard.weis@gmx.com
License: BSD
Keywords: buildout development build
Platform: UNKNOWN
Classifier: Development Status :: 3 - Alpha
Classifier: Framework :: Buildout
Classifier: Intended Audience :: Developers
Classifier: License :: OSI Approved :: BSD License
Classifier: Topic :: Software Development :: Build Tools
Classifier: Topic :: Software Development :: Libraries :: Python Modules
